ws4py/__init__.py
ws4py/_asyncio_compat.py
ws4py/async_websocket.py
ws4py/compat.py
ws4py/exc.py
ws4py/framing.py
ws4py/manager.py
ws4py/messaging.py
ws4py/streaming.py
ws4py/utf8validator.py
ws4py/websocket.py
ws4py/client/__init__.py
ws4py/client/geventclient.py
ws4py/client/threadedclient.py
ws4py/client/tornadoclient.py
ws4py/server/__init__.py
ws4py/server/cherrypyserver.py
ws4py/server/geventserver.py
ws4py/server/tulipserver.py
ws4py/server/wsgirefserver.py
ws4py/server/wsgiutils.py
ws4py_sslupdate-0.5.1b0.dist-info/LICENSE
ws4py_sslupdate-0.5.1b0.dist-info/METADATA
ws4py_sslupdate-0.5.1b0.dist-info/WHEEL
ws4py_sslupdate-0.5.1b0.dist-info/top_level.txt
ws4py_sslupdate-0.5.1b0.dist-info/RECORD
